README.rst
setup.py
redisjobs/__init__.py
redisjobs/base.py
redisjobs/utils.py
redisjobs.egg-info/PKG-INFO
redisjobs.egg-info/SOURCES.txt
redisjobs.egg-info/dependency_links.txt
redisjobs.egg-info/requires.txt
redisjobs.egg-info/top_level.txt