Metadata-Version: 1.1
Name: redisjobs
Version: 0.5.0
Summary: A Python interface to the Jobs scheduler.
Home-page: https://github.com/debrouwere/jobs.py
Author: Stijn Debrouwere
Author-email: stijn@debrouwere.org
License: ISC
Download-URL: https://github.com/debrouwere/jobs.py/tarball/master
Keywords: scheduler scheduling jobs tasks asynchronous
Platform: UNKNOWN
Classifier: Development Status :: 4 - Beta
Classifier: Intended Audience :: Developers
Classifier: License :: OSI Approved :: MIT License
Classifier: Operating System :: OS Independent
Classifier: Programming Language :: Python
